{
"meta":{"test_sets":[],"test_metrics":[],"learn_metrics":[{"best_value":"Min","name":"RMSE"}],"launch_mode":"Train","parameters":"","iteration_count":190,"learn_sets":["learn"],"name":"experiment"},
"iterations":[
{"learn":[0.9903169246],"iteration":0,"passed_time":0.009102389407,"remaining_time":1.720351598},
{"learn":[0.8790332083],"iteration":1,"passed_time":0.0135283484,"remaining_time":1.27166475},
{"learn":[0.7876228487],"iteration":2,"passed_time":0.01952820105,"remaining_time":1.217257865},
{"learn":[0.7154096839],"iteration":3,"passed_time":0.02429209168,"remaining_time":1.129582263},
{"learn":[0.6540750468],"iteration":4,"passed_time":0.03142018214,"remaining_time":1.162546739},
{"learn":[0.6068732358],"iteration":5,"passed_time":0.0406158813,"remaining_time":1.245553693},
{"learn":[0.5697233335],"iteration":6,"passed_time":0.04902516427,"remaining_time":1.281657866},
{"learn":[0.535201754],"iteration":7,"passed_time":0.05518177032,"remaining_time":1.255385275},
{"learn":[0.5106409875],"iteration":8,"passed_time":0.06160278928,"remaining_time":1.23890054},
{"learn":[0.4911070608],"iteration":9,"passed_time":0.06755745257,"remaining_time":1.216034146},
{"learn":[0.4724148823],"iteration":10,"passed_time":0.07253263529,"remaining_time":1.180303792},
{"learn":[0.4561002198],"iteration":11,"passed_time":0.07893471836,"remaining_time":1.170864989},
{"learn":[0.4430903823],"iteration":12,"passed_time":0.08441155811,"remaining_time":1.14929583},
{"learn":[0.4333683977],"iteration":13,"passed_time":0.08914497526,"remaining_time":1.120679689},
{"learn":[0.4252867198],"iteration":14,"passed_time":0.09576394718,"remaining_time":1.11724605},
{"learn":[0.416542487],"iteration":15,"passed_time":0.1009892312,"remaining_time":1.098257889},
{"learn":[0.4101591821],"iteration":16,"passed_time":0.1065417744,"remaining_time":1.084219233},
{"learn":[0.4037584368],"iteration":17,"passed_time":0.11254906,"remaining_time":1.075468795},
{"learn":[0.3962133963],"iteration":18,"passed_time":0.1177011382,"remaining_time":1.059310244},
{"learn":[0.3921836713],"iteration":19,"passed_time":0.1235006982,"remaining_time":1.049755934},
{"learn":[0.387975814],"iteration":20,"passed_time":0.1299669742,"remaining_time":1.045924697},
{"learn":[0.383843059],"iteration":21,"passed_time":0.1361379847,"remaining_time":1.039599156},
{"learn":[0.3807101434],"iteration":22,"passed_time":0.1422629532,"remaining_time":1.032952747},
{"learn":[0.3763745795],"iteration":23,"passed_time":0.1474015899,"remaining_time":1.019527664},
{"learn":[0.3728956276],"iteration":24,"passed_time":0.1533738575,"remaining_time":1.01226746},
{"learn":[0.3701904196],"iteration":25,"passed_time":0.1586613634,"remaining_time":1.000787061},
{"learn":[0.3678267354],"iteration":26,"passed_time":0.1648861698,"remaining_time":0.9954239138},
{"learn":[0.3657656692],"iteration":27,"passed_time":0.1706411473,"remaining_time":0.9872809234},
{"learn":[0.3630327359],"iteration":28,"passed_time":0.1767342475,"remaining_time":0.9811797877},
{"learn":[0.3607068382],"iteration":29,"passed_time":0.1820077903,"remaining_time":0.9707082149},
{"learn":[0.3574585081],"iteration":30,"passed_time":0.1875514862,"remaining_time":0.9619576229},
{"learn":[0.3546842124],"iteration":31,"passed_time":0.1931879081,"remaining_time":0.9538652962},
{"learn":[0.3524533218],"iteration":32,"passed_time":0.1985176843,"remaining_time":0.9444629224},
{"learn":[0.3482405949],"iteration":33,"passed_time":0.2041053559,"remaining_time":0.9364833975},
{"learn":[0.3451722968],"iteration":34,"passed_time":0.2096265424,"remaining_time":0.9283461163},
{"learn":[0.3427931368],"iteration":35,"passed_time":0.2175456337,"remaining_time":0.9306118774},
{"learn":[0.3400415266],"iteration":36,"passed_time":0.2249121008,"remaining_time":0.9300419302},
{"learn":[0.3369796283],"iteration":37,"passed_time":0.2312100627,"remaining_time":0.9248402509},
{"learn":[0.3348729259],"iteration":38,"passed_time":0.2365867336,"remaining_time":0.9160153018},
{"learn":[0.3319239238],"iteration":39,"passed_time":0.2426904159,"remaining_time":0.9100890597},
{"learn":[0.3304149367],"iteration":40,"passed_time":0.2479021085,"remaining_time":0.9009125407},
{"learn":[0.328625316],"iteration":41,"passed_time":0.2533909954,"remaining_time":0.8929016029},
{"learn":[0.3253349919],"iteration":42,"passed_time":0.2593524757,"remaining_time":0.8866235798},
{"learn":[0.3205772057],"iteration":43,"passed_time":0.2642524906,"remaining_time":0.8768378098},
{"learn":[0.316665116],"iteration":44,"passed_time":0.2706457716,"remaining_time":0.8720808195},
{"learn":[0.3145876243],"iteration":45,"passed_time":0.2795108652,"remaining_time":0.8749905345},
{"learn":[0.3123441002],"iteration":46,"passed_time":0.2859657009,"remaining_time":0.870065856},
{"learn":[0.3097495313],"iteration":47,"passed_time":0.2939348862,"remaining_time":0.8695573717},
{"learn":[0.3065214387],"iteration":48,"passed_time":0.2984260167,"remaining_time":0.8587360888},
{"learn":[0.3043619691],"iteration":49,"passed_time":0.3037211857,"remaining_time":0.8504193199},
{"learn":[0.3017777613],"iteration":50,"passed_time":0.3094230198,"remaining_time":0.8433294069},
{"learn":[0.2996722738],"iteration":51,"passed_time":0.3147770007,"remaining_time":0.8353697325},
{"learn":[0.296209221],"iteration":52,"passed_time":0.3212475022,"remaining_time":0.8303944869},
{"learn":[0.2942213488],"iteration":53,"passed_time":0.3270591445,"remaining_time":0.823704512},
{"learn":[0.293134284],"iteration":54,"passed_time":0.3326998295,"remaining_time":0.8166268542},
{"learn":[0.2903864286],"iteration":55,"passed_time":0.3387661265,"remaining_time":0.8106189456},
{"learn":[0.288169062],"iteration":56,"passed_time":0.344073765,"remaining_time":0.802838785},
{"learn":[0.2871117025],"iteration":57,"passed_time":0.3523938489,"remaining_time":0.801999794},
{"learn":[0.2864356165],"iteration":58,"passed_time":0.3582217954,"remaining_time":0.7953738169},
{"learn":[0.2850926817],"iteration":59,"passed_time":0.3634422239,"remaining_time":0.7874581519},
{"learn":[0.2824093809],"iteration":60,"passed_time":0.3691767488,"remaining_time":0.7807180426},
{"learn":[0.2802922484],"iteration":61,"passed_time":0.3740026111,"remaining_time":0.7721344229},
{"learn":[0.2788768673],"iteration":62,"passed_time":0.379185394,"remaining_time":0.7643896038},
{"learn":[0.2771017924],"iteration":63,"passed_time":0.3850345815,"remaining_time":0.7580368324},
{"learn":[0.2743679572],"iteration":64,"passed_time":0.3910732143,"remaining_time":0.7520638736},
{"learn":[0.2736266314],"iteration":65,"passed_time":0.3965280863,"remaining_time":0.7449921621},
{"learn":[0.2712687868],"iteration":66,"passed_time":0.4030731904,"remaining_time":0.7399701854},
{"learn":[0.2692143729],"iteration":67,"passed_time":0.4076179658,"remaining_time":0.7313145857},
{"learn":[0.2660287876],"iteration":68,"passed_time":0.4141826899,"remaining_time":0.7263203693},
{"learn":[0.2633271263],"iteration":69,"passed_time":0.4214656801,"remaining_time":0.7225125944},
{"learn":[0.2613776191],"iteration":70,"passed_time":0.4272820068,"remaining_time":0.7161487156},
{"learn":[0.2590106818],"iteration":71,"passed_time":0.4324820429,"remaining_time":0.7087900148},
{"learn":[0.2576952079],"iteration":72,"passed_time":0.4385481298,"remaining_time":0.7028785094},
{"learn":[0.2562093531],"iteration":73,"passed_time":0.44470609,"remaining_time":0.6971068438},
{"learn":[0.2533078096],"iteration":74,"passed_time":0.4501996915,"remaining_time":0.6903061936},
{"learn":[0.2488787706],"iteration":75,"passed_time":0.4560334319,"remaining_time":0.6840501478},
{"learn":[0.2464053168],"iteration":76,"passed_time":0.4611130968,"remaining_time":0.6766984407},
{"learn":[0.2442700019],"iteration":77,"passed_time":0.4662224282,"remaining_time":0.6694475892},
{"learn":[0.2434480856],"iteration":78,"passed_time":0.4712308379,"remaining_time":0.662109152},
{"learn":[0.2411332027],"iteration":79,"passed_time":0.4761593371,"remaining_time":0.6547190886},
{"learn":[0.2403481918],"iteration":80,"passed_time":0.4811991396,"remaining_time":0.647539583},
{"learn":[0.2380235659],"iteration":81,"passed_time":0.487767019,"remaining_time":0.6424248543},
{"learn":[0.2370523184],"iteration":82,"passed_time":0.4932412156,"remaining_time":0.6358651816},
{"learn":[0.2365538794],"iteration":83,"passed_time":0.4996346696,"remaining_time":0.6304913687},
{"learn":[0.2356901158],"iteration":84,"passed_time":0.5069764405,"remaining_time":0.6262650147},
{"learn":[0.2349156723],"iteration":85,"passed_time":0.5114976131,"remaining_time":0.618555253},
{"learn":[0.23294707],"iteration":86,"passed_time":0.5179509592,"remaining_time":0.6132063081},
{"learn":[0.2318890109],"iteration":87,"passed_time":0.5239292805,"remaining_time":0.607281666},
{"learn":[0.2297803714],"iteration":88,"passed_time":0.5286056312,"remaining_time":0.5998783005},
{"learn":[0.2276587233],"iteration":89,"passed_time":0.5345785312,"remaining_time":0.5939761458},
{"learn":[0.2266725913],"iteration":90,"passed_time":0.5395775173,"remaining_time":0.5870129035},
{"learn":[0.2250005626],"iteration":91,"passed_time":0.5447849262,"remaining_time":0.5803143779},
{"learn":[0.2221846128],"iteration":92,"passed_time":0.5506452385,"remaining_time":0.5743289047},
{"learn":[0.2214087099],"iteration":93,"passed_time":0.5555945314,"remaining_time":0.5674156916},
{"learn":[0.2193815182],"iteration":94,"passed_time":0.5603111467,"remaining_time":0.5603111467},
{"learn":[0.2176454173],"iteration":95,"passed_time":0.5667588756,"remaining_time":0.554951399},
{"learn":[0.2155951551],"iteration":96,"passed_time":0.5725844959,"remaining_time":0.5489727641},
{"learn":[0.2143920634],"iteration":97,"passed_time":0.5772820324,"remaining_time":0.5419382345},
{"learn":[0.2126300169],"iteration":98,"passed_time":0.5836556477,"remaining_time":0.5364915549},
{"learn":[0.2117939175],"iteration":99,"passed_time":0.5884988434,"remaining_time":0.529648959},
{"learn":[0.2103599837],"iteration":100,"passed_time":0.5959094767,"remaining_time":0.5251083507},
{"learn":[0.2091295511],"iteration":101,"passed_time":0.6043991435,"remaining_time":0.5214423983},
{"learn":[0.2080335252],"iteration":102,"passed_time":0.611201525,"remaining_time":0.5162575988},
{"learn":[0.206178466],"iteration":103,"passed_time":0.6173152388,"remaining_time":0.5104722167},
{"learn":[0.204576536],"iteration":104,"passed_time":0.6231133393,"remaining_time":0.5044250842},
{"learn":[0.2033086623],"iteration":105,"passed_time":0.6285911621,"remaining_time":0.4981288454},
{"learn":[0.2016483555],"iteration":106,"passed_time":0.6340043756,"remaining_time":0.4917977867},
{"learn":[0.2005735771],"iteration":107,"passed_time":0.6391190686,"remaining_time":0.4852570706},
{"learn":[0.1986873335],"iteration":108,"passed_time":0.6443507724,"remaining_time":0.478829473},
{"learn":[0.1974619836],"iteration":109,"passed_time":0.6497464418,"remaining_time":0.4725428668},
{"learn":[0.1959446732],"iteration":110,"passed_time":0.6546941799,"remaining_time":0.4659535154},
{"learn":[0.1944781422],"iteration":111,"passed_time":0.662074269,"remaining_time":0.4610874373},
{"learn":[0.1935513513],"iteration":112,"passed_time":0.6692026619,"remaining_time":0.4560053537},
{"learn":[0.1920283491],"iteration":113,"passed_time":0.6736422629,"remaining_time":0.449094842},
{"learn":[0.1909988599],"iteration":114,"passed_time":0.6804879239,"remaining_time":0.4437964721},
{"learn":[0.1903863918],"iteration":115,"passed_time":0.6875315354,"remaining_time":0.4385977036},
{"learn":[0.1887759779],"iteration":116,"passed_time":0.6937444009,"remaining_time":0.4328490707},
{"learn":[0.1875307528],"iteration":117,"passed_time":0.7013665906,"remaining_time":0.427952496},
{"learn":[0.1864376982],"iteration":118,"passed_time":0.7073504835,"remaining_time":0.4220326414},
{"learn":[0.1858396594],"iteration":119,"passed_time":0.7121941612,"remaining_time":0.415446594},
{"learn":[0.1855029393],"iteration":120,"passed_time":0.7192633214,"remaining_time":0.410158423},
{"learn":[0.184441501],"iteration":121,"passed_time":0.724738466,"remaining_time":0.4039525876},
{"learn":[0.1840379366],"iteration":122,"passed_time":0.7301293607,"remaining_time":0.3977127412},
{"learn":[0.1837268812],"iteration":123,"passed_time":0.735279533,"remaining_time":0.3913584611},
{"learn":[0.1834592722],"iteration":124,"passed_time":0.7414694318,"remaining_time":0.3855641045},
{"learn":[0.1813097327],"iteration":125,"passed_time":0.7472880555,"remaining_time":0.3795748854},
{"learn":[0.1805801069],"iteration":126,"passed_time":0.7547990644,"remaining_time":0.3744278823},
{"learn":[0.1795200847],"iteration":127,"passed_time":0.7618700944,"remaining_time":0.369030827},
{"learn":[0.1790616736],"iteration":128,"passed_time":0.767547302,"remaining_time":0.3629487242},
{"learn":[0.1780107525],"iteration":129,"passed_time":0.7725795006,"remaining_time":0.3565751541},
{"learn":[0.1773215904],"iteration":130,"passed_time":0.7785877692,"remaining_time":0.350661667},
{"learn":[0.1762565524],"iteration":131,"passed_time":0.784787438,"remaining_time":0.344830844},
{"learn":[0.1748076775],"iteration":132,"passed_time":0.7909750998,"remaining_time":0.3389893285},
{"learn":[0.1740136286],"iteration":133,"passed_time":0.7996251859,"remaining_time":0.3341717195},
{"learn":[0.1729987151],"iteration":134,"passed_time":0.8064121594,"remaining_time":0.3285382872},
{"learn":[0.17220673],"iteration":135,"passed_time":0.8142151191,"remaining_time":0.3232912973},
{"learn":[0.1709555151],"iteration":136,"passed_time":0.8196178704,"remaining_time":0.3170784462},
{"learn":[0.1700646052],"iteration":137,"passed_time":0.8252872539,"remaining_time":0.3109778058},
{"learn":[0.1691886788],"iteration":138,"passed_time":0.8306031674,"remaining_time":0.3047536801},
{"learn":[0.1684072459],"iteration":139,"passed_time":0.8358327446,"remaining_time":0.2985116945},
{"learn":[0.1677896885],"iteration":140,"passed_time":0.842700253,"remaining_time":0.2928532794},
{"learn":[0.1669704702],"iteration":141,"passed_time":0.8472112542,"remaining_time":0.286381269},
{"learn":[0.1663645368],"iteration":142,"passed_time":0.8536459479,"remaining_time":0.2805689479},
{"learn":[0.1656578342],"iteration":143,"passed_time":0.8603412853,"remaining_time":0.2748312439},
{"learn":[0.1649567038],"iteration":144,"passed_time":0.8651141742,"remaining_time":0.2684837092},
{"learn":[0.1641679482],"iteration":145,"passed_time":0.8703750479,"remaining_time":0.262304809},
{"learn":[0.1633558748],"iteration":146,"passed_time":0.8764117442,"remaining_time":0.2563653401},
{"learn":[0.1631892233],"iteration":147,"passed_time":0.8815578941,"remaining_time":0.2501718348},
{"learn":[0.1627061499],"iteration":148,"passed_time":0.8887319177,"remaining_time":0.2445503935},
{"learn":[0.1617940666],"iteration":149,"passed_time":0.8941368758,"remaining_time":0.2384365002},
{"learn":[0.1609826236],"iteration":150,"passed_time":0.8992378364,"remaining_time":0.2322534809},
{"learn":[0.1593707081],"iteration":151,"passed_time":0.9039996411,"remaining_time":0.2259999103},
{"learn":[0.1580655148],"iteration":152,"passed_time":0.9098563523,"remaining_time":0.2200306212},
{"learn":[0.1568741837],"iteration":153,"passed_time":0.9151880545,"remaining_time":0.2139400647},
{"learn":[0.1559160687],"iteration":154,"passed_time":0.9212010778,"remaining_time":0.2080131466},
{"learn":[0.1549596836],"iteration":155,"passed_time":0.9277977409,"remaining_time":0.2022123281},
{"learn":[0.1540059362],"iteration":156,"passed_time":0.93240533,"remaining_time":0.1959832859},
{"learn":[0.1531597022],"iteration":157,"passed_time":0.9379180504,"remaining_time":0.1899580862},
{"learn":[0.1523302501],"iteration":158,"passed_time":0.9432736663,"remaining_time":0.1839087022},
{"learn":[0.1519108996],"iteration":159,"passed_time":0.9496687578,"remaining_time":0.1780628921},
{"learn":[0.1503854236],"iteration":160,"passed_time":0.9561441369,"remaining_time":0.1722247203},
{"learn":[0.1499862699],"iteration":161,"passed_time":0.9640583231,"remaining_time":0.1666273645},
{"learn":[0.1488438035],"iteration":162,"passed_time":0.9703334647,"remaining_time":0.1607300831},
{"learn":[0.1477369778],"iteration":163,"passed_time":0.9756484654,"remaining_time":0.1546759762},
{"learn":[0.1472205417],"iteration":164,"passed_time":0.9805096566,"remaining_time":0.1485620692},
{"learn":[0.1463072238],"iteration":165,"passed_time":0.9853666247,"remaining_time":0.1424626445},
{"learn":[0.145057982],"iteration":166,"passed_time":0.990771969,"remaining_time":0.1364536245},
{"learn":[0.1441177495],"iteration":167,"passed_time":0.9965658013,"remaining_time":0.1305026645},
{"learn":[0.1436101849],"iteration":168,"passed_time":1.001701183,"remaining_time":0.1244717446},
{"learn":[0.1424264848],"iteration":169,"passed_time":1.009036695,"remaining_time":0.1187101994},
{"learn":[0.1414634596],"iteration":170,"passed_time":1.013895348,"remaining_time":0.1126550387},
{"learn":[0.1405505708],"iteration":171,"passed_time":1.020306308,"remaining_time":0.1067762415},
{"learn":[0.1400657628],"iteration":172,"passed_time":1.026359335,"remaining_time":0.1008561196},
{"learn":[0.1395066209],"iteration":173,"passed_time":1.033421133,"remaining_time":0.09502723059},
{"learn":[0.139111082],"iteration":174,"passed_time":1.04041805,"remaining_time":0.08917869001},
{"learn":[0.1384782958],"iteration":175,"passed_time":1.045787529,"remaining_time":0.08318764433},
{"learn":[0.1373914906],"iteration":176,"passed_time":1.052700056,"remaining_time":0.07731695326},
{"learn":[0.1366863046],"iteration":177,"passed_time":1.058300808,"remaining_time":0.07134612188},
{"learn":[0.136112533],"iteration":178,"passed_time":1.06358075,"remaining_time":0.06535971092},
{"learn":[0.1356747843],"iteration":179,"passed_time":1.070444823,"remaining_time":0.05946915684},
{"learn":[0.1349473683],"iteration":180,"passed_time":1.075668297,"remaining_time":0.05348626889},
{"learn":[0.1345811969],"iteration":181,"passed_time":1.080748985,"remaining_time":0.04750544987},
{"learn":[0.1339197533],"iteration":182,"passed_time":1.087808505,"remaining_time":0.0416101614},
{"learn":[0.1331604352],"iteration":183,"passed_time":1.092550108,"remaining_time":0.03562663394},
{"learn":[0.1326525105],"iteration":184,"passed_time":1.097905673,"remaining_time":0.02967312631},
{"learn":[0.1317031392],"iteration":185,"passed_time":1.104203354,"remaining_time":0.0237463087},
{"learn":[0.1307042513],"iteration":186,"passed_time":1.10939998,"remaining_time":0.01779786064},
{"learn":[0.1303729528],"iteration":187,"passed_time":1.116337544,"remaining_time":0.01187593132},
{"learn":[0.1301145009],"iteration":188,"passed_time":1.121990878,"remaining_time":0.005936459674},
{"learn":[0.1297784214],"iteration":189,"passed_time":1.127619185,"remaining_time":0}
]}